prettypretty-0.12.0.dist-info/METADATA
prettypretty-0.12.0.dist-info/WHEEL
prettypretty-0.12.0.dist-info/licenses/LICENSE
prettypretty.libs/libgcc_s-27e5a392.so.1
prettypretty/__init__.py
prettypretty/ansi.py
prettypretty/color.abi3.so
prettypretty/color/__init__.pyi
prettypretty/color/gamut.pyi
prettypretty/color/spectrum/__init__.pyi
prettypretty/color/spectrum/std_observer.pyi
prettypretty/color/style.pyi
prettypretty/color/termco.pyi
prettypretty/color/theme.pyi
prettypretty/darkmode.py
prettypretty/grid.py
prettypretty/ident.py
prettypretty/plot.py
prettypretty/progress.py
prettypretty/py.typed
prettypretty/terminal.py
prettypretty/theme.py
prettypretty/viz3d.py
prettypretty-0.12.0.dist-info/RECORD
