Metadata-Version: 2.4
Name: prettypretty
Version: 0.12.0
Classifier: Development Status :: 4 - Beta
Classifier: Environment :: Console
Classifier: Intended Audience :: Developers
Classifier: Intended Audience :: System Administrators
Classifier: License :: OSI Approved :: Apache Software License
Classifier: Operating System :: MacOS
Classifier: Operating System :: Microsoft :: Windows
Classifier: Operating System :: POSIX :: Linux
Classifier: Programming Language :: Python :: 3
Classifier: Programming Language :: Python :: 3.11
Classifier: Programming Language :: Python :: 3.12
Classifier: Programming Language :: Rust
Classifier: Topic :: Adaptive Technologies
Classifier: Topic :: Multimedia :: Graphics
Classifier: Topic :: Scientific/Engineering :: Human Machine Interfaces
Classifier: Topic :: Software Development :: Libraries
Classifier: Topic :: Software Development :: User Interfaces
Classifier: Topic :: System :: Shells
Classifier: Topic :: Terminals
Classifier: Topic :: Terminals :: Terminal Emulators/X Terminals
Classifier: Topic :: Utilities
Classifier: Typing :: Typed
Requires-Dist: sphinx ; extra == 'dev'
Requires-Dist: sphinxcontrib-autoprogram ; extra == 'dev'
Requires-Dist: sphinx-copybutton ; extra == 'dev'
Requires-Dist: sphinx-design ; extra == 'dev'
Requires-Dist: sphinx-rtd-theme ; extra == 'dev'
Requires-Dist: matplotlib ; extra == 'viz'
Requires-Dist: vedo ; extra == 'viz'
Provides-Extra: dev
Provides-Extra: viz
License-File: LICENSE
Summary: Applying 2020s color science to 1970s terminal user interfaces
Keywords: awesome,terminal,color,ANSI escape code,terminal user interface
Home-Page: https://crates.io/crates/prettypretty
Author-email: Robert Grimm <rgrimm@alum.mit.edu>
License: Apache 2.0
Requires-Python: >=3.11
Project-URL: repository, https://github.com/apparebit/prettypretty
Project-URL: package, https://pypi.org/project/prettypretty/
Project-URL: documentation, https://apparebit.github.io/prettypretty/
